destinepyauth/__init__.py
destinepyauth/authentication.py
destinepyauth/cli.py
destinepyauth/configs.py
destinepyauth/exceptions.py
destinepyauth/get_token.py
destinepyauth/services.py
destinepyauth/configs/cacheb.yaml
destinepyauth/configs/dea.yaml
destinepyauth/configs/eden.yaml
destinepyauth/configs/hda.yaml
destinepyauth/configs/highway.yaml
destinepyauth/configs/insula.yaml
destinepyauth/configs/polytope.yaml
destinepyauth/configs/streamer.yaml
destinepyauth-1.1.0.dist-info/licenses/LICENSE
destinepyauth-1.1.0.dist-info/METADATA
destinepyauth-1.1.0.dist-info/WHEEL
destinepyauth-1.1.0.dist-info/entry_points.txt
destinepyauth-1.1.0.dist-info/top_level.txt
destinepyauth-1.1.0.dist-info/RECORD
