Metadata-Version: 2.4
Name: destinepyauth
Version: 1.1.0
Summary: Harmonized Python script for DestinE authentication.
Author-email: David Purnell <davejpurnell@gmail.com>
License: Apache 2.0
Keywords: DestinE,authentication
Classifier: Development Status :: 4 - Beta
Classifier: License :: OSI Approved :: Apache Software License
Classifier: Programming Language :: Python :: 3
Requires-Python: >=3.9
License-File: LICENSE
Requires-Dist: conflator
Requires-Dist: lxml
Requires-Dist: pydantic
Requires-Dist: requests
Requires-Dist: authlib
Provides-Extra: dev
Requires-Dist: ruff; extra == "dev"
Requires-Dist: pre-commit; extra == "dev"
Requires-Dist: pytest; extra == "dev"
Dynamic: license-file
